okonf/__init__.py
okonf/__main__.py
okonf/utils.py
okonf/connectors/__init__.py
okonf/connectors/abstract.py
okonf/connectors/exceptions.py
okonf/connectors/local.py
okonf/connectors/ssh.py
okonf/facts/__init__.py
okonf/facts/abstract.py
okonf/facts/apt.py
okonf/facts/files.py
okonf/facts/flatpak.py
okonf/facts/git.py
okonf/facts/lxd.py
okonf/facts/multiple.py
okonf/facts/python.py
okonf/facts/systemd.py
okonf/facts/users.py
Okonf-0.2.2.dist-info/LICENSE
Okonf-0.2.2.dist-info/METADATA
Okonf-0.2.2.dist-info/WHEEL
Okonf-0.2.2.dist-info/entry_points.txt
Okonf-0.2.2.dist-info/top_level.txt
Okonf-0.2.2.dist-info/RECORD
