Metadata-Version: 2.1
Name: Okonf
Version: 0.2.2
Summary: Asynchronous configuration management based on Python Asyncio
Home-page: https://github.com/hoh/Okonf/
Author: Hugo Herter
Author-email: git@hugoherter.com
License: Apache License 2.0
Keywords: configuration management
Classifier: Development Status :: 2 - Pre-Alpha
Classifier: Environment :: Console
Classifier: Programming Language :: Python :: 3
Classifier: Intended Audience :: Developers
Classifier: Intended Audience :: System Administrators
Classifier: Intended Audience :: Information Technology
Classifier: Natural Language :: English
Classifier: Operating System :: POSIX :: Linux
Classifier: License :: OSI Approved :: Apache Software License
Classifier: Topic :: System :: Installation/Setup
Classifier: Topic :: System :: Systems Administration
License-File: LICENSE
Requires-Dist: asyncssh
Requires-Dist: aiohttp
Requires-Dist: colorama
Requires-Dist: typer
Provides-Extra: lxd
Requires-Dist: pylxd ; extra == 'lxd'
